liknorm/__init__.py
liknorm/_testit.py
liknorm/_cffi.cpython-310-aarch64-linux-gnu.so
liknorm/interface.h
liknorm/interface.c
liknorm/_machine.py
liknorm/include/liknorm.h
liknorm/lib/libliknorm.a
liknorm-2.0.0.dist-info/METADATA
liknorm-2.0.0.dist-info/RECORD
liknorm-2.0.0.dist-info/WHEEL
liknorm-2.0.0.dist-info/LICENSE.md
