Metadata-Version: 2.3
Name: liknorm
Version: 2.0.0
Summary: Liknorm Python wrapper
Home-page: https://github.com/limix/liknorm-py
License: MIT
Keywords: liknorm,integration
Author: Danilo Horta
Author-email: danilo.horta@pm.me
Requires-Python: >=3.10,<4.0
Classifier: License :: OSI Approved :: MIT License
Classifier: Programming Language :: Python :: 3
Classifier: Programming Language :: Python :: 3.10
Classifier: Programming Language :: Python :: 3.11
Classifier: Programming Language :: Python :: 3.12
Classifier: Programming Language :: Python :: 3.13
Requires-Dist: cffi (>=1.17,<2.0)
Project-URL: Repository, https://github.com/limix/liknorm-py
